React/__init__.py
React/__main__.py
React/build.py
React/futils.py
React/data/templates/public/React.brython.js
React/data/templates/public/index.html
React/data/templates/public/python-logo.svg
React/data/templates/public/react-rings-gradient.svg
React/data/templates/src/app.css
React/data/templates/src/index.css
React/data/templates/src/main.pyx
React/html_parser/__init__.py
React/html_parser/parser.py
React/pyx/__init__.py
React/pyx/parser.py
React/react/__init__.py
React/react/react.py
React/react/utils.py
react_python-0.0.14.dist-info/LICENCE
react_python-0.0.14.dist-info/LICENCE For Rudresh Veerkhare
react_python-0.0.14.dist-info/METADATA
react_python-0.0.14.dist-info/WHEEL
react_python-0.0.14.dist-info/entry_points.txt
react_python-0.0.14.dist-info/top_level.txt
react_python-0.0.14.dist-info/RECORD
