Metadata-Version: 2.1
Name: react-python
Version: 0.0.14
Summary: cLient-side react for python
Author-email: Rudresh Veerkhare <xxxx@xxx.com>, neeky <neeky@live.com>
Classifier: Programming Language :: Python :: 3
Classifier: License :: OSI Approved :: MIT License
Classifier: Operating System :: OS Independent
Requires-Python: >=3.6
License-File: LICENCE
License-File: LICENCE For Rudresh Veerkhare
Requires-Dist: pyPEG2
Requires-Dist: livereload
Requires-Dist: bs4
Requires-Dist: brython ==3.10.5
